CHANGELOG.md
activeconfigparser/ActiveConfigParser.py
activeconfigparser/HandlerParameters.py
activeconfigparser/__init__.py
activeconfigparser/unittests/__init__.py
activeconfigparser/unittests/common.py
activeconfigparser/unittests/config_test_activeconfigparser.ini
activeconfigparser/unittests/config_test_activeconfigparser_badkeys.ini
activeconfigparser/unittests/config_test_activeconfigparser_default.ini
activeconfigparser/unittests/config_test_activeconfigparser_validation_01.ini
activeconfigparser/unittests/config_test_activeconfigparser_validation_02.ini
activeconfigparser/unittests/config_test_activeconfigparser_validation_03a.ini
activeconfigparser/unittests/config_test_activeconfigparser_validation_03b.ini
activeconfigparser/unittests/test_ActiveConfigParser.py
activeconfigparser/unittests/test_HandlerParameters.py
activeconfigparser/version.py
activeconfigparser-0.9.1.1.dist-info/LICENSE
activeconfigparser-0.9.1.1.dist-info/METADATA
activeconfigparser-0.9.1.1.dist-info/WHEEL
activeconfigparser-0.9.1.1.dist-info/RECORD
