Metadata-Version: 2.1
Name: activeconfigparser
Version: 0.9.1.1
Summary: A tool that extends configparser to enable enhanced processing of .ini files.
Home-page: https://gitlab.com/semantik-software/code/python/ActiveConfigParser
License: LICENSE
Keywords: Utility,Bash,Configuration,ActiveConfigParser,ConfigParser
Author: William
Author-email: Semantik-Codeworks@outlook.com
Maintainer: William
Maintainer-email: Semantik-Codeworks@outlook.com
Requires-Python: >=3.6,<4.0
Classifier: Development Status :: 5 - Production/Stable
Classifier: Intended Audience :: Developers
Classifier: Intended Audience :: Other Audience
Classifier: Intended Audience :: System Administrators
Classifier: License :: OSI Approved :: BSD License
Classifier: License :: Other/Proprietary License
Classifier: Programming Language :: Python :: 3
Classifier: Programming Language :: Python :: 3.6
Classifier: Programming Language :: Python :: 3.7
Classifier: Programming Language :: Python :: 3.8
Classifier: Programming Language :: Python :: 3.9
Classifier: Programming Language :: Python :: 3.10
Classifier: Programming Language :: Python :: 3.11
Classifier: Programming Language :: Python :: 3 :: Only
Requires-Dist: ExceptionControl (>=0.1.0)
Requires-Dist: LightweightDebugMessages (>=0.1.0)
Requires-Dist: StronglyTypedProperty (>=0.0.2)
Project-URL: CI, https://gitlab.com/semantik-software/code/python/ActiveConfigParser/-/pipelines
Project-URL: Documentation, https://semantik-software.gitlab.io/code/python/ActiveConfigParser/
Project-URL: Issues, https://gitlab.com/semantik-software/code/python/ActiveConfigParser/-/issues
Project-URL: Repository, https://gitlab.com/semantik-software/code/python/ActiveConfigParser
